mlpype/light_gbm/__init__.py
mlpype/light_gbm/model/__init__.py
mlpype/light_gbm/model/lightgbm_model.py
mlpype_lightgbm-0.6.12.dist-info/METADATA
mlpype_lightgbm-0.6.12.dist-info/WHEEL
mlpype_lightgbm-0.6.12.dist-info/RECORD
