Metadata-Version: 2.4
Name: mlpype-lightgbm
Version: 0.6.12
Summary: LightGBM extension for MLpype
Author: Jeroen van den Hoven
License: MIT
Requires-Python: >=3.9
Requires-Dist: lightgbm>=4.3.0
Requires-Dist: mlpype-base
Requires-Dist: mlpype-sklearn
Provides-Extra: strict
Requires-Dist: lightgbm==4.3.0; extra == 'strict'
